utils/__init__.py
utils/chunk_analyzer.py
utils/chunk_joiner.py
splitview-0.0.1.dist-info/LICENSE
splitview-0.0.1.dist-info/METADATA
splitview-0.0.1.dist-info/WHEEL
splitview-0.0.1.dist-info/top_level.txt
splitview-0.0.1.dist-info/RECORD
